[{"TrackId":1,"SongId":2},{"TrackId":2,"SongId":3},{"TrackId":2,"SongId":4},{"TrackId":3,"SongId":5},{"TrackId":3,"SongId":6},{"TrackId":3,"SongId":7},{"TrackId":5,"SongId":8},{"TrackId":6,"SongId":9},{"TrackId":7,"SongId":6},{"TrackId":8,"SongId":10},{"TrackId":9,"SongId":11},{"TrackId":11,"SongId":12},{"TrackId":14,"SongId":13},{"TrackId":14,"SongId":14},{"TrackId":14,"SongId":15},{"TrackId":14,"SongId":16},{"TrackId":14,"SongId":17},{"TrackId":14,"SongId":18},{"TrackId":14,"SongId":19},{"TrackId":15,"SongId":20},{"TrackId":15,"SongId":21},{"TrackId":15,"SongId":22},{"TrackId":15,"SongId":133},{"TrackId":15,"SongId":134},{"TrackId":15,"SongId":135},{"TrackId":15,"SongId":136},{"TrackId":16,"SongId":23},{"TrackId":16,"SongId":24},{"TrackId":16,"SongId":25},{"TrackId":16,"SongId":26},{"TrackId":16,"SongId":27},{"TrackId":17,"SongId":29},{"TrackId":17,"SongId":137},{"TrackId":18,"SongId":30},{"TrackId":18,"SongId":32},{"TrackId":19,"SongId":34},{"TrackId":19,"SongId":138},{"TrackId":20,"SongId":36},{"TrackId":20,"SongId":139},{"TrackId":20,"SongId":141},{"TrackId":21,"SongId":38},{"TrackId":21,"SongId":137},{"TrackId":22,"SongId":142},{"TrackId":22,"SongId":143},{"TrackId":22,"SongId":156},{"TrackId":23,"SongId":40},{"TrackId":23,"SongId":43},{"TrackId":23,"SongId":44},{"TrackId":23,"SongId":144},{"TrackId":23,"SongId":157},{"TrackId":28,"SongId":45},{"TrackId":30,"SongId":45},{"TrackId":31,"SongId":45},{"TrackId":32,"SongId":40},{"TrackId":32,"SongId":146},{"TrackId":33,"SongId":145},{"TrackId":36,"SongId":147},{"TrackId":37,"SongId":147},{"TrackId":38,"SongId":158},{"TrackId":39,"SongId":148},{"TrackId":40,"SongId":160},{"TrackId":41,"SongId":48},{"TrackId":42,"SongId":161},{"TrackId":43,"SongId":3},{"TrackId":43,"SongId":49},{"TrackId":43,"SongId":50},{"TrackId":43,"SongId":51},{"TrackId":43,"SongId":52},{"TrackId":44,"SongId":43},{"TrackId":44,"SongId":52},{"TrackId":45,"SongId":52},{"TrackId":45,"SongId":53},{"TrackId":45,"SongId":54},{"TrackId":45,"SongId":55},{"TrackId":46,"SongId":4},{"TrackId":46,"SongId":56},{"TrackId":46,"SongId":57},{"TrackId":46,"SongId":58},{"TrackId":46,"SongId":59},{"TrackId":47,"SongId":60},{"TrackId":47,"SongId":61},{"TrackId":47,"SongId":62},{"TrackId":47,"SongId":63},{"TrackId":47,"SongId":162},{"TrackId":48,"SongId":64},{"TrackId":48,"SongId":65},{"TrackId":48,"SongId":66},{"TrackId":48,"SongId":68},{"TrackId":48,"SongId":70},{"TrackId":48,"SongId":71},{"TrackId":48,"SongId":72},{"TrackId":48,"SongId":73},{"TrackId":48,"SongId":74},{"TrackId":48,"SongId":76},{"TrackId":48,"SongId":163},{"TrackId":49,"SongId":79},{"TrackId":49,"SongId":82},{"TrackId":49,"SongId":84},{"TrackId":49,"SongId":149},{"TrackId":49,"SongId":150},{"TrackId":49,"SongId":151},{"TrackId":49,"SongId":152},{"TrackId":49,"SongId":168},{"TrackId":50,"SongId":85},{"TrackId":50,"SongId":86},{"TrackId":50,"SongId":87},{"TrackId":50,"SongId":88},{"TrackId":51,"SongId":89},{"TrackId":51,"SongId":90},{"TrackId":51,"SongId":91},{"TrackId":51,"SongId":93},{"TrackId":51,"SongId":154},{"TrackId":52,"SongId":95},{"TrackId":52,"SongId":96},{"TrackId":52,"SongId":97},{"TrackId":52,"SongId":170},{"TrackId":53,"SongId":98},{"TrackId":53,"SongId":99},{"TrackId":53,"SongId":100},{"TrackId":54,"SongId":24},{"TrackId":54,"SongId":101},{"TrackId":54,"SongId":102},{"TrackId":54,"SongId":103},{"TrackId":54,"SongId":104},{"TrackId":54,"SongId":105},{"TrackId":54,"SongId":106},{"TrackId":54,"SongId":155},{"TrackId":55,"SongId":19},{"TrackId":55,"SongId":107},{"TrackId":55,"SongId":110},{"TrackId":55,"SongId":111},{"TrackId":55,"SongId":112},{"TrackId":55,"SongId":113},{"TrackId":55,"SongId":171},{"TrackId":55,"SongId":172},{"TrackId":58,"SongId":114},{"TrackId":58,"SongId":115},{"TrackId":58,"SongId":116},{"TrackId":59,"SongId":66},{"TrackId":59,"SongId":117},{"TrackId":59,"SongId":118},{"TrackId":59,"SongId":119},{"TrackId":60,"SongId":120},{"TrackId":60,"SongId":121},{"TrackId":60,"SongId":122},{"TrackId":60,"SongId":124},{"TrackId":60,"SongId":125},{"TrackId":61,"SongId":126},{"TrackId":62,"SongId":127},{"TrackId":62,"SongId":128},{"TrackId":62,"SongId":129},{"TrackId":62,"SongId":130},{"TrackId":63,"SongId":46},{"TrackId":63,"SongId":131},{"TrackId":63,"SongId":132}]